nlptxtools/__init__.py
nlptxtools-0.0.5.dist-info/LICENSE
nlptxtools-0.0.5.dist-info/METADATA
nlptxtools-0.0.5.dist-info/WHEEL
nlptxtools-0.0.5.dist-info/top_level.txt
nlptxtools-0.0.5.dist-info/RECORD
