Metadata-Version: 2.1
Name: nlptxtools
Version: 0.0.5
Summary: NLP tools for Russian language
Home-page: https://github.com/Midriaz/nlptxtools
Author: Midriaz
Author-email: scome@inbox.ru
License: UNKNOWN
Platform: UNKNOWN
Requires-Python: >=3.6
